pgactivity/__init__.py
pgactivity/__main__.py
pgactivity/activities.py
pgactivity/cli.py
pgactivity/colors.py
pgactivity/compat.py
pgactivity/config.py
pgactivity/data.py
pgactivity/handlers.py
pgactivity/keys.py
pgactivity/pg.py
pgactivity/types.py
pgactivity/ui.py
pgactivity/utils.py
pgactivity/views.py
pgactivity/widgets.py
pgactivity/profiles/minimal.conf
pgactivity/profiles/narrow.conf
pgactivity/profiles/wide.conf
pgactivity/queries/__init__.py
pgactivity/queries/disable_log_min_duration_sample.sql
pgactivity/queries/disable_log_min_duration_statement.sql
pgactivity/queries/do_pg_cancel_backend.sql
pgactivity/queries/do_pg_terminate_backend.sql
pgactivity/queries/get_blocking_oldest.sql
pgactivity/queries/get_blocking_post_090200.sql
pgactivity/queries/get_blocking_post_090600.sql
pgactivity/queries/get_data_directory.sql
pgactivity/queries/get_pg_activity_oldest.sql
pgactivity/queries/get_pg_activity_post_090200.sql
pgactivity/queries/get_pg_activity_post_090400.sql
pgactivity/queries/get_pg_activity_post_090600.sql
pgactivity/queries/get_pg_activity_post_100000.sql
pgactivity/queries/get_pg_activity_post_110000.sql
pgactivity/queries/get_pg_activity_post_130000.sql
pgactivity/queries/get_pga_inet_addresses.sql
pgactivity/queries/get_replication_slots_post_140000.sql
pgactivity/queries/get_server_info_oldest.sql
pgactivity/queries/get_server_info_post_090100.sql
pgactivity/queries/get_server_info_post_090200.sql
pgactivity/queries/get_server_info_post_090400.sql
pgactivity/queries/get_server_info_post_090600.sql
pgactivity/queries/get_server_info_post_100000.sql
pgactivity/queries/get_server_info_post_110000.sql
pgactivity/queries/get_temporary_files_oldest.sql
pgactivity/queries/get_temporary_files_post_090100.sql
pgactivity/queries/get_temporary_files_post_090500.sql
pgactivity/queries/get_temporary_files_post_120000.sql
pgactivity/queries/get_version.sql
pgactivity/queries/get_waiting_oldest.sql
pgactivity/queries/get_waiting_post_090200.sql
pg_activity-3.6.0.dist-info/AUTHORS.md
pg_activity-3.6.0.dist-info/LICENSE.txt
pg_activity-3.6.0.dist-info/METADATA
pg_activity-3.6.0.dist-info/WHEEL
pg_activity-3.6.0.dist-info/entry_points.txt
pg_activity-3.6.0.dist-info/top_level.txt
pg_activity-3.6.0.dist-info/RECORD
