Metadata-Version: 2.2
Name: pg-activity
Version: 3.6.0
Summary: Command line tool for PostgreSQL server activity monitoring.
Author-email: Julien Tachoires <julmon@gmail.com>, Benoit Lobréau <benoit.lobreau@dalibo.com>, Denis Laxalde <denis.laxalde@dalibo.com>, Dalibo <contact@dalibo.com>
Maintainer-email: Denis Laxalde <denis.laxalde@dalibo.com>, Benoit Lobréau <benoit.lobreau@dalibo.com>
License: PostgreSQL
Project-URL: Bug Tracker, https://github.com/dalibo/pg_activity/issues/
Project-URL: Changelog, https://github.com/dalibo/pg_activity/blob/master/CHANGELOG.md
Project-URL: Homepage, https://github.com/dalibo/pg_activity
Project-URL: Source code, https://github.com/dalibo/pg_activity/
Keywords: activity,cli,monitoring,postgresql,sql,top
Classifier: Development Status :: 5 - Production/Stable
Classifier: Environment :: Console
Classifier: Environment :: Console :: Curses
Classifier: License :: OSI Approved :: PostgreSQL License
Classifier: Programming Language :: Python :: 3
Classifier: Topic :: Database
Requires-Python: >=3.9
License-File: LICENSE.txt
License-File: AUTHORS.md
Requires-Dist: attrs!=21.1,>=17.4
Requires-Dist: blessed>=1.15.0
Requires-Dist: humanize!=4.12.0,>=0.5.1
Requires-Dist: psutil>=2.0.0
Provides-Extra: dev
Requires-Dist: pg-activity[psycopg,psycopg2,testing,typing]; extra == "dev"
Requires-Dist: black>=24.10.0; extra == "dev"
Requires-Dist: check-manifest; extra == "dev"
Requires-Dist: codespell; extra == "dev"
Requires-Dist: flake8; extra == "dev"
Requires-Dist: isort; extra == "dev"
Requires-Dist: pre-commit; extra == "dev"
Requires-Dist: pyupgrade; extra == "dev"
Provides-Extra: typing
Requires-Dist: mypy; extra == "typing"
Requires-Dist: types-psutil>=5.9.5.15; extra == "typing"
Requires-Dist: types-psycopg2; extra == "typing"
Requires-Dist: types-setuptools; extra == "typing"
Provides-Extra: psycopg
Requires-Dist: psycopg[binary]>=3.1; extra == "psycopg"
Provides-Extra: psycopg2
Requires-Dist: psycopg2-binary>=2.8; extra == "psycopg2"
Provides-Extra: testing
Requires-Dist: psycopg[binary]; extra == "testing"
Requires-Dist: pytest; extra == "testing"
Requires-Dist: pytest-postgresql>=4.0; extra == "testing"
